consumers/__init__.py
consumers-0.6.1.dist-info/METADATA
consumers-0.6.1.dist-info/RECORD
consumers-0.6.1.dist-info/WHEEL
consumers-0.6.1.dist-info/top_level.txt
consumers-0.6.1.dist-info/zip-safe
