Metadata-Version: 1.1
Name: consumers
Version: 0.6.1
Summary: A simple, flexible way to parallelize processing in Python.
Home-page: https://github.com/nvllsvm/consumers
Author: Andrew Rabert
Author-email: arabert@nullsum.net
License: Apache 2.0
Platform: UNKNOWN
Classifier: Development Status :: 4 - Beta
Classifier: Intended Audience :: Developers
Classifier: License :: OSI Approved :: Apache Software License
Classifier: Programming Language :: Python :: 3 :: Only
